{"0": {"code": "0", "name": "M\u5927\u53a6A\u5ea7501", "children": {"0": {"code": "00", "name": "501F00"}, "1": {"code": "01", "name": "501F01"}, "2": {"code": "02", "name": "501F02"}, "3": {"code": "03", "name": "501F03"}, "4": {"code": "04", "name": "501F04"}, "5": {"code": "05", "name": "501F05"}, "6": {"code": "06", "name": "501F06"}, "7": {"code": "07", "name": "501F07"}, "8": {"code": "08", "name": "501F08"}, "9": {"code": "09", "name": "501F09"}, "10": {"code": "010", "name": "501F010"}, "11": {"code": "011", "name": "501F011"}, "12": {"code": "012", "name": "501F012"}, "13": {"code": "013", "name": "501F013"}, "14": {"code": "014", "name": "501F014"}, "15": {"code": "015", "name": "501F015"}, "16": {"code": "016", "name": "501F016"}, "17": {"code": "017", "name": "501F017"}, "18": {"code": "018", "name": "501F018"}, "19": {"code": "019", "name": "501F019"}, "20": {"code": "020", "name": "501F020"}, "21": {"code": "021", "name": "501F021"}, "22": {"code": "022", "name": "501F022"}, "23": {"code": "023", "name": "501F023"}, "24": {"code": "024", "name": "501F024"}, "25": {"code": "025", "name": "501F025"}, "26": {"code": "026", "name": "501F026"}, "27": {"code": "027", "name": "501F027"}, "28": {"code": "028", "name": "501F028"}, "29": {"code": "029", "name": "501F029"}, "30": {"code": "030", "name": "501F030"}, "31": {"code": "031", "name": "501F031"}, "32": {"code": "032", "name": "501F032"}, "33": {"code": "033", "name": "501F033"}, "34": {"code": "034", "name": "501F034"}, "35": {"code": "035", "name": "501F035"}, "36": {"code": "036", "name": "501F036"}, "37": {"code": "037", "name": "501F037"}, "38": {"code": "038", "name": "501F038"}, "39": {"code": "039", "name": "501F039"}, "40": {"code": "040", "name": "501F040"}, "41": {"code": "041", "name": "501F041"}, "42": {"code": "042", "name": "501F042"}, "43": {"code": "043", "name": "501F043"}, "44": {"code": "044", "name": "501F044"}, "45": {"code": "045", "name": "501F045"}, "46": {"code": "046", "name": "501F046"}, "47": {"code": "047", "name": "501F047"}, "48": {"code": "048", "name": "501F048"}, "49": {"code": "049", "name": "501F049"}}}, "1": {"code": "1", "name": "M\u5927\u53a6A\u5ea7615", "children": {"0": {"code": "10", "name": "615F00"}, "1": {"code": "11", "name": "615F01"}, "2": {"code": "12", "name": "615F02"}, "3": {"code": "13", "name": "615F03"}, "4": {"code": "14", "name": "615F04"}, "5": {"code": "15", "name": "615F05"}, "6": {"code": "16", "name": "615F06"}, "7": {"code": "17", "name": "615F07"}, "8": {"code": "18", "name": "615F08"}, "9": {"code": "19", "name": "615F09"}, "10": {"code": "110", "name": "615F010"}, "11": {"code": "111", "name": "615F011"}, "12": {"code": "112", "name": "615F012"}, "13": {"code": "113", "name": "615F013"}, "14": {"code": "114", "name": "615F014"}, "15": {"code": "115", "name": "615F015"}, "16": {"code": "116", "name": "615F016"}, "17": {"code": "117", "name": "615F017"}, "18": {"code": "118", "name": "615F018"}, "19": {"code": "119", "name": "615F019"}, "20": {"code": "120", "name": "615F020"}, "21": {"code": "121", "name": "615F021"}, "22": {"code": "122", "name": "615F022"}, "23": {"code": "123", "name": "615F023"}, "24": {"code": "124", "name": "615F024"}, "25": {"code": "125", "name": "615F025"}, "26": {"code": "126", "name": "615F026"}, "27": {"code": "127", "name": "615F027"}, "28": {"code": "128", "name": "615F028"}, "29": {"code": "129", "name": "615F029"}, "30": {"code": "130", "name": "615F030"}, "31": {"code": "131", "name": "615F031"}, "32": {"code": "132", "name": "615F032"}, "33": {"code": "133", "name": "615F033"}, "34": {"code": "134", "name": "615F034"}, "35": {"code": "135", "name": "615F035"}, "36": {"code": "136", "name": "615F036"}, "37": {"code": "137", "name": "615F037"}, "38": {"code": "138", "name": "615F038"}, "39": {"code": "139", "name": "615F039"}, "40": {"code": "140", "name": "615F040"}, "41": {"code": "141", "name": "615F041"}, "42": {"code": "142", "name": "615F042"}, "43": {"code": "143", "name": "615F043"}, "44": {"code": "144", "name": "615F044"}, "45": {"code": "145", "name": "615F045"}, "46": {"code": "146", "name": "615F046"}, "47": {"code": "147", "name": "615F047"}, "48": {"code": "148", "name": "615F048"}, "49": {"code": "149", "name": "615F049"}}}}